{
  "data": [{
    "attributes": {
      "privacyDetails": {
        "managePrivacyChoicesUrl": null,
        "privacyTypes": []
      }
    },
    "href": "/v1/catalog/de/apps/1458873480?l=de-DE",
    "id": "1458873480",
    "relationships": {
      "developer": {
        "data": [{
          "href": "/v1/catalog/de/developers/1460275196?l=de-DE",
          "id": "1460275196",
          "type": "developers"
        }],
        "href": "/v1/catalog/de/apps/1458873480/developer?l=de-DE"
      },
      "genres": {
        "data": [{
          "href": "/v1/catalog/de/genres/6000?l=de-DE",
          "id": "6000",
          "type": "genres"
        }, {
          "href": "/v1/catalog/de/genres/6007?l=de-DE",
          "id": "6007",
          "type": "genres"
        }],
        "href": "/v1/catalog/de/apps/1458873480/genres?l=de-DE"
      }
    },
    "type": "apps"
  }]
}