{
  "data": [{
    "attributes": {
      "privacyDetails": {
        "managePrivacyChoicesUrl": null,
        "privacyTypes": []
      }
    },
    "href": "/v1/catalog/de/apps/1438041720?l=de-DE",
    "id": "1438041720",
    "relationships": {
      "developer": {
        "data": [{
          "href": "/v1/catalog/de/developers/903158763?l=de-DE",
          "id": "903158763",
          "type": "developers"
        }],
        "href": "/v1/catalog/de/apps/1438041720/developer?l=de-DE"
      },
      "genres": {
        "data": [{
          "href": "/v1/catalog/de/genres/6002?l=de-DE",
          "id": "6002",
          "type": "genres"
        }, {
          "href": "/v1/catalog/de/genres/6009?l=de-DE",
          "id": "6009",
          "type": "genres"
        }],
        "href": "/v1/catalog/de/apps/1438041720/genres?l=de-DE"
      }
    },
    "type": "apps"
  }]
}