{
  "data": [{
    "attributes": {
      "privacyDetails": {
        "managePrivacyChoicesUrl": null,
        "privacyTypes": [{
          "dataCategories": [],
          "description": "Der Entwickler erfasst keine Daten von dieser App.",
          "identifier": "DATA_NOT_COLLECTED",
          "privacyType": "Keine Daten erfasst",
          "purposes": []
        }]
      }
    },
    "href": "/v1/catalog/de/apps/1441195209?l=de-DE",
    "id": "1441195209",
    "relationships": {
      "developer": {
        "data": [{
          "href": "/v1/catalog/de/developers/1441195208?l=de-DE",
          "id": "1441195208",
          "type": "developers"
        }],
        "href": "/v1/catalog/de/apps/1441195209/developer?l=de-DE"
      },
      "genres": {
        "data": [{
          "href": "/v1/catalog/de/genres/6002?l=de-DE",
          "id": "6002",
          "type": "genres"
        }, {
          "href": "/v1/catalog/de/genres/6003?l=de-DE",
          "id": "6003",
          "type": "genres"
        }],
        "href": "/v1/catalog/de/apps/1441195209/genres?l=de-DE"
      }
    },
    "type": "apps"
  }]
}