{
  "data": [{
    "attributes": {
      "privacyDetails": {
        "managePrivacyChoicesUrl": null,
        "privacyTypes": []
      }
    },
    "href": "/v1/catalog/de/apps/854413379?l=de-DE",
    "id": "854413379",
    "relationships": {
      "developer": {
        "data": [{
          "href": "/v1/catalog/de/developers/854413382?l=de-DE",
          "id": "854413382",
          "type": "developers"
        }],
        "href": "/v1/catalog/de/apps/854413379/developer?l=de-DE"
      },
      "genres": {
        "data": [{
          "href": "/v1/catalog/de/genres/6006?l=de-DE",
          "id": "6006",
          "type": "genres"
        }, {
          "href": "/v1/catalog/de/genres/6017?l=de-DE",
          "id": "6017",
          "type": "genres"
        }],
        "href": "/v1/catalog/de/apps/854413379/genres?l=de-DE"
      }
    },
    "type": "apps"
  }]
}