{
  "data": [{
    "attributes": {
      "privacyDetails": {
        "managePrivacyChoicesUrl": null,
        "privacyTypes": [{
          "dataCategories": [],
          "description": "Die folgenden Daten, die zwar möglicherweise erfasst, aber nicht mit deiner Identität verknüpft werden, können für die folgenden Zwecke verwendet werden:",
          "identifier": "DATA_NOT_LINKED_TO_YOU",
          "privacyType": "Nicht mit dir verknüpfte Daten",
          "purposes": [{
            "dataCategories": [{
              "dataCategory": "Standort",
              "dataTypes": ["Genauer Standort"],
              "identifier": "LOCATION"
            }, {
              "dataCategory": "Kennungen",
              "dataTypes": ["Geräte-ID"],
              "identifier": "IDENTIFIERS"
            }],
            "identifier": "THIRD_PARTY_ADVERTISING",
            "purpose": "Drittanbieter-Werbung"
          }]
        }]
      }
    },
    "href": "/v1/catalog/de/apps/959254082?l=de-DE",
    "id": "959254082",
    "relationships": {
      "developer": {
        "data": [{
          "href": "/v1/catalog/de/developers/727632745?l=de-DE",
          "id": "727632745",
          "type": "developers"
        }],
        "href": "/v1/catalog/de/apps/959254082/developer?l=de-DE"
      },
      "genres": {
        "data": [{
          "href": "/v1/catalog/de/genres/6008?l=de-DE",
          "id": "6008",
          "type": "genres"
        }, {
          "href": "/v1/catalog/de/genres/6005?l=de-DE",
          "id": "6005",
          "type": "genres"
        }],
        "href": "/v1/catalog/de/apps/959254082/genres?l=de-DE"
      }
    },
    "type": "apps"
  }]
}