{
  "data": [{
    "attributes": {
      "privacyDetails": {
        "managePrivacyChoicesUrl": null,
        "privacyTypes": []
      }
    },
    "href": "/v1/catalog/de/apps/633298943?l=de-DE",
    "id": "633298943",
    "relationships": {
      "developer": {
        "data": [{
          "href": "/v1/catalog/de/developers/972563884?l=de-DE",
          "id": "972563884",
          "type": "developers"
        }],
        "href": "/v1/catalog/de/apps/633298943/developer?l=de-DE"
      },
      "genres": {
        "data": [{
          "href": "/v1/catalog/de/genres/6011?l=de-DE",
          "id": "6011",
          "type": "genres"
        }, {
          "href": "/v1/catalog/de/genres/6016?l=de-DE",
          "id": "6016",
          "type": "genres"
        }],
        "href": "/v1/catalog/de/apps/633298943/genres?l=de-DE"
      }
    },
    "type": "apps"
  }]
}