{
  "data": [{
    "attributes": {
      "privacyDetails": {
        "managePrivacyChoicesUrl": null,
        "privacyTypes": [{
          "dataCategories": [],
          "description": "Der Entwickler erfasst keine Daten von dieser App.",
          "identifier": "DATA_NOT_COLLECTED",
          "privacyType": "Keine Daten erfasst",
          "purposes": []
        }]
      }
    },
    "href": "/v1/catalog/de/apps/1470369690?l=de-DE",
    "id": "1470369690",
    "relationships": {
      "developer": {
        "data": [{
          "href": "/v1/catalog/de/developers/1456255051?l=de-DE",
          "id": "1456255051",
          "type": "developers"
        }],
        "href": "/v1/catalog/de/apps/1470369690/developer?l=de-DE"
      },
      "genres": {
        "data": [{
          "href": "/v1/catalog/de/genres/6004?l=de-DE",
          "id": "6004",
          "type": "genres"
        }],
        "href": "/v1/catalog/de/apps/1470369690/genres?l=de-DE"
      }
    },
    "type": "apps"
  }]
}