{
  "data": [{
    "attributes": {
      "privacyDetails": {
        "managePrivacyChoicesUrl": null,
        "privacyTypes": []
      }
    },
    "href": "/v1/catalog/de/apps/943864757?l=de-DE",
    "id": "943864757",
    "relationships": {
      "developer": {
        "data": [{
          "href": "/v1/catalog/de/developers/390606207?l=de-DE",
          "id": "390606207",
          "type": "developers"
        }],
        "href": "/v1/catalog/de/apps/943864757/developer?l=de-DE"
      },
      "genres": {
        "data": [{
          "href": "/v1/catalog/de/genres/6004?l=de-DE",
          "id": "6004",
          "type": "genres"
        }, {
          "href": "/v1/catalog/de/genres/6012?l=de-DE",
          "id": "6012",
          "type": "genres"
        }],
        "href": "/v1/catalog/de/apps/943864757/genres?l=de-DE"
      }
    },
    "type": "apps"
  }]
}