{
  "data": [{
    "attributes": {
      "privacyDetails": {
        "managePrivacyChoicesUrl": null,
        "privacyTypes": []
      }
    },
    "href": "/v1/catalog/de/apps/1462173561?l=de-DE",
    "id": "1462173561",
    "relationships": {
      "developer": {
        "data": [{
          "href": "/v1/catalog/de/developers/1163760703?l=de-DE",
          "id": "1163760703",
          "type": "developers"
        }],
        "href": "/v1/catalog/de/apps/1462173561/developer?l=de-DE"
      },
      "genres": {
        "data": [{
          "href": "/v1/catalog/de/genres/6024?l=de-DE",
          "id": "6024",
          "type": "genres"
        }],
        "href": "/v1/catalog/de/apps/1462173561/genres?l=de-DE"
      }
    },
    "type": "apps"
  }]
}