{
  "data": [{
    "attributes": {
      "privacyDetails": {
        "managePrivacyChoicesUrl": null,
        "privacyTypes": []
      }
    },
    "href": "/v1/catalog/de/apps/1447992270?l=de-DE",
    "id": "1447992270",
    "relationships": {
      "developer": {
        "data": [{
          "href": "/v1/catalog/de/developers/1441823333?l=de-DE",
          "id": "1441823333",
          "type": "developers"
        }],
        "href": "/v1/catalog/de/apps/1447992270/developer?l=de-DE"
      },
      "genres": {
        "data": [{
          "href": "/v1/catalog/de/genres/6000?l=de-DE",
          "id": "6000",
          "type": "genres"
        }, {
          "href": "/v1/catalog/de/genres/6007?l=de-DE",
          "id": "6007",
          "type": "genres"
        }],
        "href": "/v1/catalog/de/apps/1447992270/genres?l=de-DE"
      }
    },
    "type": "apps"
  }]
}